firecrawl/__init__.py
firecrawl/client.py
firecrawl/firecrawl.backup.py
firecrawl/types.py
firecrawl/__tests__/e2e/v2/conftest.py
firecrawl/__tests__/e2e/v2/test_async.py
firecrawl/__tests__/e2e/v2/test_batch_scrape.py
firecrawl/__tests__/e2e/v2/test_crawl.py
firecrawl/__tests__/e2e/v2/test_extract.py
firecrawl/__tests__/e2e/v2/test_map.py
firecrawl/__tests__/e2e/v2/test_scrape.py
firecrawl/__tests__/e2e/v2/test_search.py
firecrawl/__tests__/e2e/v2/test_usage.py
firecrawl/__tests__/e2e/v2/test_watcher.py
firecrawl/__tests__/e2e/v2/aio/conftest.py
firecrawl/__tests__/e2e/v2/aio/test_aio_batch_scrape.py
firecrawl/__tests__/e2e/v2/aio/test_aio_crawl.py
firecrawl/__tests__/e2e/v2/aio/test_aio_extract.py
firecrawl/__tests__/e2e/v2/aio/test_aio_map.py
firecrawl/__tests__/e2e/v2/aio/test_aio_scrape.py
firecrawl/__tests__/e2e/v2/aio/test_aio_search.py
firecrawl/__tests__/e2e/v2/aio/test_aio_usage.py
firecrawl/__tests__/e2e/v2/aio/test_aio_watcher.py
firecrawl/__tests__/unit/test_recursive_schema_v1.py
firecrawl/__tests__/unit/v2/methods/test_agent.py
firecrawl/__tests__/unit/v2/methods/test_agent_request_preparation.py
firecrawl/__tests__/unit/v2/methods/test_agent_webhook.py
firecrawl/__tests__/unit/v2/methods/test_batch_request_preparation.py
firecrawl/__tests__/unit/v2/methods/test_branding.py
firecrawl/__tests__/unit/v2/methods/test_crawl_params.py
firecrawl/__tests__/unit/v2/methods/test_crawl_request_preparation.py
firecrawl/__tests__/unit/v2/methods/test_crawl_validation.py
firecrawl/__tests__/unit/v2/methods/test_map_request_preparation.py
firecrawl/__tests__/unit/v2/methods/test_pagination.py
firecrawl/__tests__/unit/v2/methods/test_scrape_request_preparation.py
firecrawl/__tests__/unit/v2/methods/test_search_request_preparation.py
firecrawl/__tests__/unit/v2/methods/test_search_validation.py
firecrawl/__tests__/unit/v2/methods/test_usage_types.py
firecrawl/__tests__/unit/v2/methods/test_webhook.py
firecrawl/__tests__/unit/v2/methods/aio/test_aio_crawl_params.py
firecrawl_py-4.14.0.dist-info/licenses/LICENSE
firecrawl_py-4.14.0.dist-info/METADATA
firecrawl_py-4.14.0.dist-info/WHEEL
firecrawl_py-4.14.0.dist-info/top_level.txt
firecrawl_py-4.14.0.dist-info/RECORD
